Metadata-Version: 2.4
Name: robotframework-appiumwindows
Version: 0.1.0
Summary: Robot Framework AppiumLibrary extension for Windows desktop automation using NovaWindows Driver instead of WinAppDriver.
Author-email: Huy Nguyen <nguyenvanhuy0612@gmail.com>
License: MIT
Project-URL: Homepage, https://github.com/nguyenvanhuy0612/robotframework-appiumwindows
Project-URL: Repository, https://github.com/nguyenvanhuy0612/robotframework-appiumwindows
Project-URL: Issues, https://github.com/nguyenvanhuy0612/robotframework-appiumwindows/issues
Classifier: Development Status :: 3 - Alpha
Classifier: Framework :: Robot Framework
Classifier: Framework :: Robot Framework :: Library
Classifier: Programming Language :: Python :: 3
Classifier: Programming Language :: Python :: 3.10
Classifier: Programming Language :: Python :: 3.11
Classifier: Programming Language :: Python :: 3.12
Classifier: Operating System :: Microsoft :: Windows
Classifier: License :: OSI Approved :: MIT License
Classifier: Intended Audience :: Developers
Classifier: Topic :: Software Development :: Testing
Classifier: Topic :: Software Development :: Quality Assurance
Classifier: Topic :: Software Development :: Libraries :: Python Modules
Requires-Python: >=3.10
License-File: LICENSE
Requires-Dist: robotframework>=7.3.2
Requires-Dist: Appium-Python-Client>=5.1.1
Dynamic: license-file
